saagieapi/__init__.py
saagieapi/apps/__init__.py
saagieapi/apps/apps.py
saagieapi/apps/gql_queries.py
saagieapi/docker_credentials/__init__.py
saagieapi/docker_credentials/docker_credentials.py
saagieapi/docker_credentials/gql_queries.py
saagieapi/env_vars/__init__.py
saagieapi/env_vars/env_vars.py
saagieapi/env_vars/gql_queries.py
saagieapi/gql_queries.py
saagieapi/groups/__init__.py
saagieapi/groups/groups.py
saagieapi/jobs/__init__.py
saagieapi/jobs/gql_queries.py
saagieapi/jobs/jobs.py
saagieapi/pipelines/__init__.py
saagieapi/pipelines/gql_queries.py
saagieapi/pipelines/graph_pipeline.py
saagieapi/pipelines/pipelines.py
saagieapi/profiles/__init__.py
saagieapi/profiles/profiles.py
saagieapi/projects/__init__.py
saagieapi/projects/gql_queries.py
saagieapi/projects/projects.py
saagieapi/repositories/__init__.py
saagieapi/repositories/gql_queries.py
saagieapi/repositories/repositories.py
saagieapi/saagie_api.py
saagieapi/storages/__init__.py
saagieapi/storages/gql_queries.py
saagieapi/storages/storages.py
saagieapi/users/__init__.py
saagieapi/users/users.py
saagieapi/utils/__init__.py
saagieapi/utils/bearer_auth.py
saagieapi/utils/folder_functions.py
saagieapi/utils/gql_client.py
saagieapi/utils/request_client.py
saagieapi/utils/rich_console.py
saagieapi-2.13.1.dist-info/LICENSE
saagieapi-2.13.1.dist-info/METADATA
saagieapi-2.13.1.dist-info/WHEEL
saagieapi-2.13.1.dist-info/RECORD
