Metadata-Version: 2.3
Name: saagieapi
Version: 2.13.1
Summary: Python API to interact with Saagie
License: GLWTPL
Author: Saagie
Requires-Python: >=3.10,<4.0
Classifier: License :: Other/Proprietary License
Classifier: Programming Language :: Python :: 3
Classifier: Programming Language :: Python :: 3.10
Classifier: Programming Language :: Python :: 3.11
Classifier: Programming Language :: Python :: 3.12
Classifier: Programming Language :: Python :: 3.13
Requires-Dist: croniter (>=1.0.1,<2.0.0)
Requires-Dist: deprecation (>=2.1.0,<3.0.0)
Requires-Dist: gql (>=3.0.0,<4.0.0)
Requires-Dist: pytz (>=2021.1)
Requires-Dist: requests (==2.29.0)
Requires-Dist: requests_toolbelt (>=0.9.1,<0.10.0)
Requires-Dist: rich (>=12.3.0,<13.0.0)
Project-URL: Repository, https://github.com/saagie/api-saagie
